pacti/__init__.py
pacti/__version__.py
pacti/contracts/__init__.py
pacti/contracts/polyhedral_iocontract.py
pacti/contracts/smt_iocontract.py
pacti/iocontract/__init__.py
pacti/iocontract/compundiocontract.py
pacti/iocontract/iocontract.py
pacti/terms/__init__.py
pacti/terms/polyhedra/__init__.py
pacti/terms/polyhedra/polyhedra.py
pacti/terms/polyhedra/serializer.py
pacti/terms/polyhedra/syntax/__init__.py
pacti/terms/polyhedra/syntax/data.py
pacti/terms/polyhedra/syntax/grammar.py
pacti/terms/smt/__init__.py
pacti/terms/smt/smt.py
pacti/utils/__init__.py
pacti/utils/errors.py
pacti/utils/fileio.py
pacti/utils/lists.py
pacti/utils/plots.py
Pacti-0.2.0.dist-info/WHEEL
Pacti-0.2.0.dist-info/METADATA
Pacti-0.2.0.dist-info/licenses/LICENSE
Pacti-0.2.0.dist-info/RECORD
