Metadata-Version: 2.1
Name: Pacti
Version: 0.2.0
Summary: A package for compositional system analysis and design
License: BSD-3-Clause
Keywords: system design,contracts,compositional
Author-email: Pacti developers <info@pacti.org>
Requires-Python: >=3.8, <3.12
Classifier: Topic :: Scientific/Engineering
Requires-Dist: matplotlib>=3.6.2
Requires-Dist: numpy>=1.24.1
Requires-Dist: pyparsing>=3.0.9
Requires-Dist: scipy>=1.10.0
Requires-Dist: sympy>=1.11.1
Requires-Dist: typing-extensions>=4.5.0
Requires-Dist: z3-solver>=4.15.1.0
Project-URL: Bug Tracker, https://github.com/pacti-org/pacti/issues
Project-URL: documentation, https://www.pacti.org
Project-URL: repository, https://github.com/pacti-org/pacti
